requirejs.py
django_compressor_requirejs-0.3.dist-info/DESCRIPTION.rst
django_compressor_requirejs-0.3.dist-info/METADATA
django_compressor_requirejs-0.3.dist-info/metadata.json
django_compressor_requirejs-0.3.dist-info/RECORD
django_compressor_requirejs-0.3.dist-info/top_level.txt
django_compressor_requirejs-0.3.dist-info/WHEEL
requirejs/__init__.py
requirejs/filter.py
requirejs/finder.py
requirejs/tests.py
requirejs/utils.py
