Metadata-Version: 2.0
Name: django-compressor-requirejs
Version: 0.3
Summary: Compress requirejs-modules into bundles.
Home-page: http://github.com/bpeschier/django-compressor-requirejs
Author: Bas Peschier
Author-email: bpeschier@fizzgig.nl
License: MIT
Platform: UNKNOWN
Classifier: Development Status :: 4 - Beta
Classifier: Intended Audience :: Developers
Classifier: License :: OSI Approved :: MIT License
Classifier: Programming Language :: Python :: 2.7
Classifier: Programming Language :: Python :: 3.3
Classifier: Programming Language :: Python :: 3.4
Classifier: Topic :: Software Development :: Libraries :: Python Modules
Requires-Dist: Django (>=1.6)
Requires-Dist: django-compressor (>=1.4)
